genmake/__init__.py
genmake/__main__.py
genmake/args.py
genmake/build_rules.py
genmake/cli.py
genmake/config.py
genmake/genmake.py
genmake/makefile.py
genmake/source_file_maker.py
genmake/update.py
genmake-1.1.6.dist-info/LICENSE.md
genmake-1.1.6.dist-info/METADATA
genmake-1.1.6.dist-info/WHEEL
genmake-1.1.6.dist-info/entry_points.txt
genmake-1.1.6.dist-info/top_level.txt
genmake-1.1.6.dist-info/RECORD
