Metadata-Version: 2.1
Name: genmake
Version: 1.1.6
Summary: Generate Makefile for C Project of 42 School
Home-page: https://github.com/arthur-trt/genMake
Author: Arthur - 42 Student
Author-email: atrouill@student.42.fr
License: UNKNOWN
Project-URL: Bug Reports, https://github.com/arthur-trt/genMake/issues
Project-URL: Source, https://github.com/arthur-trt/genMake/
Keywords: makefile c
Platform: UNKNOWN
Classifier: Development Status :: 3 - Alpha
Classifier: Intended Audience :: Developers
Classifier: Topic :: Software Development :: Build Tools
Classifier: License :: OSI Approved :: The Unlicense (Unlicense)
Classifier: Programming Language :: Python :: 3.5
Classifier: Programming Language :: Python :: 3.6
Classifier: Programming Language :: Python :: 3.7
Requires-Python: >=3.5, <4
License-File: LICENSE.md
Requires-Dist: colorama (==0.4.4)
Requires-Dist: requests
Provides-Extra: dev
